pyVali/__init__.py
pyVali-0.1.1.dist-info/LICENSE
pyVali-0.1.1.dist-info/METADATA
pyVali-0.1.1.dist-info/WHEEL
pyVali-0.1.1.dist-info/top_level.txt
pyVali-0.1.1.dist-info/RECORD
