Metadata-Version: 2.1
Name: pyVali
Version: 0.1.1
Summary: python parameter validate
Home-page: https://github.com/gpsbird/pyVali
Author: gpsbird
Author-email: gpsbird@qq.com
License: UNKNOWN
Platform: UNKNOWN
Classifier: Programming Language :: Python :: 3
Classifier: License :: OSI Approved :: MIT License
Classifier: Operating System :: OS Independent
Requires-Python: >=3.6
